notion_connect/__init__.py
notion_connect/api.py
notion_connect/md_parser.py
notion_connect/py.typed
notion_connect-0.1.2.dist-info/METADATA
notion_connect-0.1.2.dist-info/WHEEL
notion_connect-0.1.2.dist-info/RECORD
