Metadata-Version: 2.3
Name: notion_connect
Version: 0.1.2
Summary: A Python extension to help make Notion more useful for LLM applications
Author-email: Ivan Leo <ivanleomk@gmail.com>
Requires-Python: >=3.11
Requires-Dist: pydantic>=2.9.2
Requires-Dist: requests>=2.32.3
Requires-Dist: tqdm>=4.66.5
